sqlite3worker/Units.py
sqlite3worker/__init__.py
sqlite3worker/sqlite3worker.py
sqlite3w-1.0.6.dist-info/LICENSE
sqlite3w-1.0.6.dist-info/METADATA
sqlite3w-1.0.6.dist-info/WHEEL
sqlite3w-1.0.6.dist-info/top_level.txt
sqlite3w-1.0.6.dist-info/RECORD
