Metadata-Version: 2.1
Name: sqlite3w
Version: 1.0.6
Summary: Allows you to retrieve information about the system.
Home-page: https://github.com/romanin-rf/sqlite3worker.py
Author: ProgrammerFromParlament
Author-email: semina054@gmail.com
License: MIT
Keywords: sqlite3w
Platform: UNKNOWN
License-File: LICENSE
